kemlglearn/__init__.py
kemlglearn/cluster/GlobalKMeans.py
kemlglearn/cluster/KMedoidsFlexible.py
kemlglearn/cluster/KModes.py
kemlglearn/cluster/KPrototypes.py
kemlglearn/cluster/KernelKMeans.py
kemlglearn/cluster/Leader.py
kemlglearn/cluster/__init__.py
kemlglearn/cluster/test.py
kemlglearn/cluster/border/BorderDetection.py
kemlglearn/cluster/border/__init__.py
kemlglearn/cluster/consensus/MeanPartition.py
kemlglearn/cluster/consensus/SimpleConsensusClustering.py
kemlglearn/cluster/consensus/__init__.py
kemlglearn/cluster/consensus/test.py
kemlglearn/datasets/__init__.py
kemlglearn/datasets/samples_generator.py
kemlglearn/feature_selection/__init__.py
kemlglearn/feature_selection/unsupervised/LaplacianScore.py
kemlglearn/feature_selection/unsupervised/__init__.py
kemlglearn/feature_selection/unsupervised/test.py
kemlglearn/metrics/Xu.py
kemlglearn/metrics/__init__.py
kemlglearn/metrics/cluster.py
kemlglearn/metrics/divergences.py
kemlglearn/metrics/nestedpartition.py
kemlglearn/metrics/quantization_error.py
kemlglearn/metrics/test.py
kemlglearn/preprocessing/Discretizer.py
kemlglearn/preprocessing/Imputer.py
kemlglearn/preprocessing/__init__.py
kemlglearn/preprocessing/test.py
kemlglearn/time_series/__init__.py
kemlglearn/time_series/decomposition/MFT.py
kemlglearn/time_series/decomposition/STFT.py
kemlglearn/time_series/decomposition/__init__.py
kemlglearn/time_series/discretization/BOSS.py
kemlglearn/time_series/discretization/SAX.py
kemlglearn/time_series/discretization/__init__.py
kemlglearn/time_series/smoothing/Smoothing.py
kemlglearn/time_series/smoothing/__init__.py
kemlglearn-0.4.3.dist-info/LICENSE
kemlglearn-0.4.3.dist-info/METADATA
kemlglearn-0.4.3.dist-info/WHEEL
kemlglearn-0.4.3.dist-info/top_level.txt
kemlglearn-0.4.3.dist-info/RECORD
