Metadata-Version: 2.1
Name: kemlglearn
Version: 0.4.3
Summary: Machine Learning algorithms/functions 
Home-page: http://www.cs.upc.edu/~bejar
Author: Javier Bejar
Author-email: bejar@cs.upc.edu
License: GPL 2.0
License-File: LICENSE
